LICENSE.txt
MANIFEST.in
README.rst
development.pip
requirements.pip
setup.py
bin/karbon
bin/migrate
bin/schema_debug
bin/schema_test
bin/torus
torus/__init__.py
torus/aggregates.py
torus/configuration.py
torus/exceptions.py
torus/karbon_tcp.py
torus/schema.py
torus/util.py
torus/web.py
torus.egg-info/PKG-INFO
torus.egg-info/SOURCES.txt
torus.egg-info/dependency_links.txt
torus.egg-info/requires.txt
torus.egg-info/top_level.txt