Metadata-Version: 1.1
Name: torus
Version: 0.7.1
Summary: Carbon and Graphite replacement using Kairos for timeseries storage
Home-page: https://github.com/agoragames/torus
Author: Aaron Westendorf
Author-email: aaron@agoragames.com
License: LICENSE.txt
Keywords: python,redis,mongo,sql,mysql,sqlite,postgresql,cassandra,time,timeseries,gevent,graphite,carbon,rrd,statistics
Platform: UNKNOWN
Classifier: Development Status :: 4 - Beta
Classifier: License :: OSI Approved :: BSD License
Classifier: Intended Audience :: Developers
Classifier: Operating System :: POSIX
Classifier: Topic :: Communications
Classifier: Topic :: System :: Distributed Computing
Classifier: Topic :: Software Development :: Libraries :: Python Modules
Classifier: Programming Language :: Python
Classifier: Programming Language :: Python :: 2.7
Classifier: Topic :: Software Development :: Libraries
